{".class":"MypyFile","_fullname":"scripts.lc_marc_update","future_import_flags":[],"is_partial_stub_package":false,"is_stub":false,"names":{".class":"SymbolTable","BadImport":{".class":"SymbolTableNode","kind":"Gdef","node":{".class":"Var","flags":["is_suppressed_import","is_ready","is_inferred"],"fullname":"scripts.lc_marc_update.BadImport","name":"BadImport","type":{".class":"AnyType","missing_import_name":"scripts.lc_marc_update.BadImport","source_any":null,"type_of_any":3}}},"FTP":{".class":"SymbolTableNode","cross_ref":"ftplib.FTP","kind":"Gdef"},"__annotations__":{".class":"SymbolTableNode","kind":"Gdef","node":{".class":"Var","flags":["is_ready"],"fullname":"scripts.lc_marc_update.__annotations__","name":"__annotations__","type":{".class":"Instance","args":["builtins.str",{".class":"AnyType","missing_import_name":null,"source_any":null,"type_of_any":6}],"extra_attrs":null,"type_ref":"builtins.dict"}}},"__doc__":{".class":"SymbolTableNode","kind":"Gdef","node":{".class":"Var","flags":["is_ready"],"fullname":"scripts.lc_marc_update.__doc__","name":"__doc__","type":"builtins.str"}},"__file__":{".class":"SymbolTableNode","kind":"Gdef","node":{".class":"Var","flags":["is_ready"],"fullname":"scripts.lc_marc_update.__file__","name":"__file__","type":"builtins.str"}},"__name__":{".class":"SymbolTableNode","kind":"Gdef","node":{".class":"Var","flags":["is_ready"],"fullname":"scripts.lc_marc_update.__name__","name":"__name__","type":"builtins.str"}},"__package__":{".class":"SymbolTableNode","kind":"Gdef","node":{".class":"Var","flags":["is_ready"],"fullname":"scripts.lc_marc_update.__package__","name":"__package__","type":"builtins.str"}},"__spec__":{".class":"SymbolTableNode","kind":"Gdef","node":{".class":"Var","flags":["is_ready"],"fullname":"scripts.lc_marc_update.__spec__","name":"__spec__","type":"_frozen_importlib.ModuleSpec"}},"argparse":{".class":"SymbolTableNode","cross_ref":"argparse","kind":"Gdef"},"args":{".class":"SymbolTableNode","kind":"Gdef","node":{".class":"Var","flags":["is_inferred","has_explicit_value"],"fullname":"scripts.lc_marc_update.args","name":"args","type":"argparse.Namespace"}},"attempt":{".class":"SymbolTableNode","kind":"Gdef","node":{".class":"Var","flags":["is_index_var","is_inferred"],"fullname":"scripts.lc_marc_update.attempt","name":"attempt","type":"builtins.int"}},"attempts":{".class":"SymbolTableNode","kind":"Gdef","node":{".class":"Var","flags":["is_ready","is_inferred","has_explicit_value"],"fullname":"scripts.lc_marc_update.attempts","name":"attempts","type":"builtins.int"}},"bad":{".class":"SymbolTableNode","kind":"Gdef","node":{".class":"Var","flags":["is_inferred","has_explicit_value"],"fullname":"scripts.lc_marc_update.bad","name":"bad","type":{".class":"Instance","args":["_io._WrappedBuffer"],"extra_attrs":null,"type_ref":"_io.TextIOWrapper"}}},"base_url":{".class":"SymbolTableNode","kind":"Gdef","node":{".class":"Var","flags":["is_ready","is_inferred","has_explicit_value"],"fullname":"scripts.lc_marc_update.base_url","name":"base_url","type":"builtins.str"}},"body":{".class":"SymbolTableNode","kind":"Gdef","node":{".class":"Var","flags":["is_inferred","has_explicit_value"],"fullname":"scripts.lc_marc_update.body","name":"body","type":{".class":"AnyType","missing_import_name":"scripts.lc_marc_update.httplib","source_any":{".class":"AnyType","missing_import_name":"scripts.lc_marc_update.httplib","source_any":null,"type_of_any":3},"type_of_any":7}}},"c":{".class":"SymbolTableNode","kind":"Gdef","node":{".class":"Var","flags":["is_inferred","has_explicit_value"],"fullname":"scripts.lc_marc_update.c","name":"c","type":{".class":"AnyType","missing_import_name":null,"source_any":null,"type_of_any":6}}},"con":{".class":"SymbolTableNode","kind":"Gdef","node":{".class":"Var","flags":["is_inferred","has_explicit_value"],"fullname":"scripts.lc_marc_update.con","name":"con","type":{".class":"AnyType","missing_import_name":"scripts.lc_marc_update.httplib","source_any":{".class":"AnyType","missing_import_name":"scripts.lc_marc_update.httplib","source_any":null,"type_of_any":3},"type_of_any":7}}},"config":{".class":"SymbolTableNode","cross_ref":"openlibrary.config","kind":"Gdef"},"config_file":{".class":"SymbolTableNode","kind":"Gdef","node":{".class":"Var","flags":["is_inferred","has_explicit_value"],"fullname":"scripts.lc_marc_update.config_file","name":"config_file","type":{".class":"AnyType","missing_import_name":null,"source_any":null,"type_of_any":2}}},"data":{".class":"SymbolTableNode","kind":"Gdef","node":{".class":"Var","flags":["is_ready","is_inferred","has_explicit_value"],"fullname":"scripts.lc_marc_update.data","name":"data","type":"builtins.str"}},"etree":{".class":"SymbolTableNode","kind":"Gdef","node":{".class":"Var","flags":["is_suppressed_import","is_ready","is_inferred"],"fullname":"scripts.lc_marc_update.etree","name":"etree","type":{".class":"AnyType","missing_import_name":"scripts.lc_marc_update.etree","source_any":null,"type_of_any":3}}},"existing":{".class":"SymbolTableNode","kind":"Gdef","node":{".class":"Var","flags":["is_inferred","has_explicit_value"],"fullname":"scripts.lc_marc_update.existing","name":"existing","type":{".class":"Instance","args":[{".class":"AnyType","missing_import_name":"scripts.lc_marc_update.etree","source_any":{".class":"AnyType","missing_import_name":"scripts.lc_marc_update.etree","source_any":null,"type_of_any":3},"type_of_any":7}],"extra_attrs":null,"type_ref":"builtins.set"}}},"f":{".class":"SymbolTableNode","kind":"Gdef","node":{".class":"Var","flags":["is_index_var","is_inferred"],"fullname":"scripts.lc_marc_update.f","name":"f","type":{".class":"AnyType","missing_import_name":null,"source_any":null,"type_of_any":1}}},"ftp":{".class":"SymbolTableNode","kind":"Gdef","node":{".class":"Var","flags":["is_inferred","has_explicit_value"],"fullname":"scripts.lc_marc_update.ftp","name":"ftp","type":"ftplib.FTP"}},"h1":{".class":"SymbolTableNode","kind":"Gdef","node":{".class":"Var","flags":["is_inferred","has_explicit_value"],"fullname":"scripts.lc_marc_update.h1","name":"h1","type":{".class":"AnyType","missing_import_name":"scripts.lc_marc_update.httplib","source_any":{".class":"AnyType","missing_import_name":"scripts.lc_marc_update.httplib","source_any":null,"type_of_any":3},"type_of_any":7}}},"headers":{".class":"SymbolTableNode","kind":"Gdef","node":{".class":"Var","flags":["is_inferred","has_explicit_value"],"fullname":"scripts.lc_marc_update.headers","name":"headers","type":{".class":"Instance","args":["builtins.str",{".class":"AnyType","missing_import_name":null,"source_any":{".class":"AnyType","missing_import_name":null,"source_any":null,"type_of_any":1},"type_of_any":7}],"extra_attrs":null,"type_ref":"builtins.dict"}}},"host":{".class":"SymbolTableNode","kind":"Gdef","node":{".class":"Var","flags":["is_ready","is_inferred","has_explicit_value"],"fullname":"scripts.lc_marc_update.host","name":"host","type":"builtins.str"}},"httplib":{".class":"SymbolTableNode","kind":"Gdef","node":{".class":"Var","flags":["is_suppressed_import","is_ready","is_inferred"],"fullname":"scripts.lc_marc_update.httplib","name":"httplib","type":{".class":"AnyType","missing_import_name":"scripts.lc_marc_update.httplib","source_any":null,"type_of_any":3}}},"import_api_url":{".class":"SymbolTableNode","kind":"Gdef","node":{".class":"Var","flags":["is_inferred","has_explicit_value"],"fullname":"scripts.lc_marc_update.import_api_url","name":"import_api_url","type":"builtins.str"}},"internal_error":{".class":"SymbolTableNode","kind":"Gdef","node":{".class":"Var","flags":["is_ready","is_inferred","has_explicit_value"],"fullname":"scripts.lc_marc_update.internal_error","name":"internal_error","type":"builtins.str"}},"item_id":{".class":"SymbolTableNode","kind":"Gdef","node":{".class":"Var","flags":["is_ready","is_inferred","has_explicit_value"],"fullname":"scripts.lc_marc_update.item_id","name":"item_id","type":"builtins.str"}},"iter_marc":{".class":"SymbolTableNode","kind":"Gdef","node":{".class":"FuncDef","abstract_status":0,"arg_kinds":[0],"arg_names":["data"],"dataclass_transform_spec":null,"deprecated":null,"flags":["is_generator"],"fullname":"scripts.lc_marc_update.iter_marc","name":"iter_marc","type":null}},"json":{".class":"SymbolTableNode","cross_ref":"json","kind":"Gdef"},"length":{".class":"SymbolTableNode","kind":"Gdef","node":{".class":"Var","flags":["is_inferred","has_explicit_value"],"fullname":"scripts.lc_marc_update.length","name":"length","type":{".class":"AnyType","missing_import_name":null,"source_any":{".class":"AnyType","missing_import_name":null,"source_any":null,"type_of_any":1},"type_of_any":7}}},"loc":{".class":"SymbolTableNode","kind":"Gdef","node":{".class":"Var","flags":["is_inferred","has_explicit_value"],"fullname":"scripts.lc_marc_update.loc","name":"loc","type":"builtins.str"}},"loc_file":{".class":"SymbolTableNode","kind":"Gdef","node":{".class":"Var","flags":["is_inferred","has_explicit_value"],"fullname":"scripts.lc_marc_update.loc_file","name":"loc_file","type":{".class":"AnyType","missing_import_name":null,"source_any":{".class":"AnyType","missing_import_name":null,"source_any":null,"type_of_any":1},"type_of_any":7}}},"login":{".class":"SymbolTableNode","kind":"Gdef","node":{".class":"FuncDef","abstract_status":0,"arg_kinds":[0,0],"arg_names":["h1","password"],"dataclass_transform_spec":null,"deprecated":null,"flags":[],"fullname":"scripts.lc_marc_update.login","name":"login","type":null}},"lxml":{".class":"SymbolTableNode","kind":"Gdef","node":{".class":"Var","flags":["is_suppressed_import","is_ready","is_inferred"],"fullname":"scripts.lc_marc_update.lxml","name":"lxml","type":{".class":"AnyType","missing_import_name":"scripts.lc_marc_update.lxml","source_any":null,"type_of_any":3}}},"marc_data":{".class":"SymbolTableNode","kind":"Gdef","node":{".class":"Var","flags":["is_inferred","has_explicit_value"],"fullname":"scripts.lc_marc_update.marc_data","name":"marc_data","type":{".class":"AnyType","missing_import_name":null,"source_any":{".class":"AnyType","missing_import_name":null,"source_any":null,"type_of_any":1},"type_of_any":7}}},"no_bucket_error":{".class":"SymbolTableNode","kind":"Gdef","node":{".class":"Var","flags":["is_ready","is_inferred","has_explicit_value"],"fullname":"scripts.lc_marc_update.no_bucket_error","name":"no_bucket_error","type":"builtins.str"}},"parser":{".class":"SymbolTableNode","kind":"Gdef","node":{".class":"Var","flags":["is_inferred","has_explicit_value"],"fullname":"scripts.lc_marc_update.parser","name":"parser","type":"argparse.ArgumentParser"}},"pos":{".class":"SymbolTableNode","kind":"Gdef","node":{".class":"Var","flags":["is_inferred","has_explicit_value"],"fullname":"scripts.lc_marc_update.pos","name":"pos","type":{".class":"AnyType","missing_import_name":null,"source_any":{".class":"AnyType","missing_import_name":null,"source_any":null,"type_of_any":1},"type_of_any":7}}},"print_line":{".class":"SymbolTableNode","kind":"Gdef","node":{".class":"FuncDef","abstract_status":0,"arg_kinds":[0],"arg_names":["f"],"dataclass_transform_spec":null,"deprecated":null,"flags":[],"fullname":"scripts.lc_marc_update.print_line","name":"print_line","type":null}},"put_file":{".class":"SymbolTableNode","kind":"Gdef","node":{".class":"FuncDef","abstract_status":0,"arg_kinds":[0,0,0,0],"arg_names":["con","ia","filename","data"],"dataclass_transform_spec":null,"deprecated":null,"flags":[],"fullname":"scripts.lc_marc_update.put_file","name":"put_file","type":null}},"read_block":{".class":"SymbolTableNode","kind":"Gdef","node":{".class":"FuncDef","abstract_status":0,"arg_kinds":[0],"arg_names":["block"],"dataclass_transform_spec":null,"deprecated":null,"flags":[],"fullname":"scripts.lc_marc_update.read_block","name":"read_block","type":null}},"read_rc":{".class":"SymbolTableNode","kind":"Gdef","node":{".class":"Var","flags":["is_suppressed_import","is_ready","is_inferred"],"fullname":"scripts.lc_marc_update.read_rc","name":"read_rc","type":{".class":"AnyType","missing_import_name":"scripts.lc_marc_update.read_rc","source_any":null,"type_of_any":3}}},"reply":{".class":"SymbolTableNode","kind":"Gdef","node":{".class":"Var","flags":["is_inferred","has_explicit_value"],"fullname":"scripts.lc_marc_update.reply","name":"reply","type":{".class":"AnyType","missing_import_name":null,"source_any":null,"type_of_any":2}}},"res":{".class":"SymbolTableNode","kind":"Gdef","node":{".class":"Var","flags":["is_inferred","has_explicit_value"],"fullname":"scripts.lc_marc_update.res","name":"res","type":{".class":"AnyType","missing_import_name":"scripts.lc_marc_update.httplib","source_any":{".class":"AnyType","missing_import_name":"scripts.lc_marc_update.httplib","source_any":null,"type_of_any":3},"type_of_any":7}}},"root":{".class":"SymbolTableNode","kind":"Gdef","node":{".class":"Var","flags":["is_inferred","has_explicit_value"],"fullname":"scripts.lc_marc_update.root","name":"root","type":{".class":"AnyType","missing_import_name":"scripts.lc_marc_update.etree","source_any":{".class":"AnyType","missing_import_name":"scripts.lc_marc_update.etree","source_any":null,"type_of_any":3},"type_of_any":7}}},"sleep":{".class":"SymbolTableNode","cross_ref":"time.sleep","kind":"Gdef"},"sys":{".class":"SymbolTableNode","cross_ref":"sys","kind":"Gdef"},"to_upload":{".class":"SymbolTableNode","kind":"Gdef","node":{".class":"Var","flags":["is_inferred","has_explicit_value"],"fullname":"scripts.lc_marc_update.to_upload","name":"to_upload","type":{".class":"Instance","args":[{".class":"AnyType","missing_import_name":null,"source_any":null,"type_of_any":1}],"extra_attrs":null,"type_ref":"builtins.set"}}},"url":{".class":"SymbolTableNode","kind":"Gdef","node":{".class":"Var","flags":["is_ready","is_inferred","has_explicit_value"],"fullname":"scripts.lc_marc_update.url","name":"url","type":"builtins.str"}},"wait":{".class":"SymbolTableNode","kind":"Gdef","node":{".class":"Var","flags":["is_ready","is_inferred","has_explicit_value"],"fullname":"scripts.lc_marc_update.wait","name":"wait","type":"builtins.int"}},"welcome":{".class":"SymbolTableNode","kind":"Gdef","node":{".class":"Var","flags":["is_inferred","has_explicit_value"],"fullname":"scripts.lc_marc_update.welcome","name":"welcome","type":"builtins.str"}}},"path":"scripts\\lc_marc_update.py"}