{".class":"MypyFile","_fullname":"scripts.solr_dump_xisbn","future_import_flags":[],"is_partial_stub_package":false,"is_stub":false,"names":{".class":"SymbolTable","AsyncGenerator":{".class":"SymbolTableNode","cross_ref":"typing.AsyncGenerator","kind":"Gdef"},"FnToCLI":{".class":"SymbolTableNode","cross_ref":"scripts.solr_builder.solr_builder.fn_to_cli.FnToCLI","kind":"Gdef"},"Literal":{".class":"SymbolTableNode","cross_ref":"typing.Literal","kind":"Gdef"},"__annotations__":{".class":"SymbolTableNode","kind":"Gdef","node":{".class":"Var","flags":["is_ready"],"fullname":"scripts.solr_dump_xisbn.__annotations__","name":"__annotations__","type":{".class":"Instance","args":["builtins.str",{".class":"AnyType","missing_import_name":null,"source_any":null,"type_of_any":6}],"extra_attrs":null,"type_ref":"builtins.dict"}}},"__doc__":{".class":"SymbolTableNode","kind":"Gdef","node":{".class":"Var","flags":["is_ready"],"fullname":"scripts.solr_dump_xisbn.__doc__","name":"__doc__","type":"builtins.str"}},"__file__":{".class":"SymbolTableNode","kind":"Gdef","node":{".class":"Var","flags":["is_ready"],"fullname":"scripts.solr_dump_xisbn.__file__","name":"__file__","type":"builtins.str"}},"__name__":{".class":"SymbolTableNode","kind":"Gdef","node":{".class":"Var","flags":["is_ready"],"fullname":"scripts.solr_dump_xisbn.__name__","name":"__name__","type":"builtins.str"}},"__package__":{".class":"SymbolTableNode","kind":"Gdef","node":{".class":"Var","flags":["is_ready"],"fullname":"scripts.solr_dump_xisbn.__package__","name":"__package__","type":"builtins.str"}},"__spec__":{".class":"SymbolTableNode","kind":"Gdef","node":{".class":"Var","flags":["is_ready"],"fullname":"scripts.solr_dump_xisbn.__spec__","name":"__spec__","type":"_frozen_importlib.ModuleSpec"}},"asyncio":{".class":"SymbolTableNode","cross_ref":"asyncio","kind":"Gdef"},"fetch_docs":{".class":"SymbolTableNode","kind":"Gdef","node":{".class":"FuncDef","abstract_status":0,"arg_kinds":[0,0,1],"arg_names":["params","solr_base","page_size"],"dataclass_transform_spec":null,"deprecated":null,"flags":["is_coroutine"],"fullname":"scripts.solr_dump_xisbn.fetch_docs","name":"fetch_docs","type":{".class":"CallableType","arg_kinds":[0,0,1],"arg_names":["params","solr_base","page_size"],"arg_types":[{".class":"Instance","args":["builtins.str",{".class":"UnionType","items":["builtins.str","builtins.int"],"uses_pep604_syntax":true}],"extra_attrs":null,"type_ref":"builtins.dict"},"builtins.str",{".class":"AnyType","missing_import_name":null,"source_any":null,"type_of_any":1}],"bound_args":[],"def_extras":{"first_arg":null},"fallback":"builtins.function","from_concatenate":false,"implicit":false,"imprecise_arg_kinds":false,"is_ellipsis_args":false,"name":"fetch_docs","ret_type":{".class":"Instance","args":[{".class":"AnyType","missing_import_name":null,"source_any":null,"type_of_any":6},{".class":"AnyType","missing_import_name":null,"source_any":null,"type_of_any":6},{".class":"Instance","args":[{".class":"Instance","args":[{".class":"AnyType","missing_import_name":null,"source_any":null,"type_of_any":4},{".class":"AnyType","missing_import_name":null,"source_any":null,"type_of_any":4}],"extra_attrs":null,"type_ref":"builtins.dict"}],"extra_attrs":null,"type_ref":"builtins.list"}],"extra_attrs":null,"type_ref":"typing.Coroutine"},"type_guard":null,"type_is":null,"unpack_kwargs":false,"variables":[]}}},"httpx":{".class":"SymbolTableNode","kind":"Gdef","node":{".class":"Var","flags":["is_suppressed_import","is_ready","is_inferred"],"fullname":"scripts.solr_dump_xisbn.httpx","name":"httpx","type":{".class":"AnyType","missing_import_name":"scripts.solr_dump_xisbn.httpx","source_any":null,"type_of_any":3}}},"main":{".class":"SymbolTableNode","kind":"Gdef","node":{".class":"FuncDef","abstract_status":0,"arg_kinds":[1,1,1,1],"arg_names":["solr_base","workers","page_size","id_field"],"dataclass_transform_spec":null,"deprecated":null,"flags":["is_coroutine"],"fullname":"scripts.solr_dump_xisbn.main","name":"main","type":{".class":"CallableType","arg_kinds":[1,1,1,1],"arg_names":["solr_base","workers","page_size","id_field"],"arg_types":[{".class":"AnyType","missing_import_name":null,"source_any":null,"type_of_any":1},{".class":"AnyType","missing_import_name":null,"source_any":null,"type_of_any":1},{".class":"AnyType","missing_import_name":null,"source_any":null,"type_of_any":1},{".class":"UnionType","items":[{".class":"LiteralType","fallback":"builtins.str","value":"isbn"},{".class":"LiteralType","fallback":"builtins.str","value":"lccn"}],"uses_pep604_syntax":false}],"bound_args":[],"def_extras":{"first_arg":null},"fallback":"builtins.function","from_concatenate":false,"implicit":false,"imprecise_arg_kinds":false,"is_ellipsis_args":false,"name":"main","ret_type":{".class":"Instance","args":[{".class":"AnyType","missing_import_name":null,"source_any":null,"type_of_any":6},{".class":"AnyType","missing_import_name":null,"source_any":null,"type_of_any":6},{".class":"NoneType"}],"extra_attrs":null,"type_ref":"typing.Coroutine"},"type_guard":null,"type_is":null,"unpack_kwargs":false,"variables":[]}}},"stream_bounds":{".class":"SymbolTableNode","kind":"Gdef","node":{".class":"FuncDef","abstract_status":0,"arg_kinds":[0,0,1],"arg_names":["params","solr_base","page_size"],"dataclass_transform_spec":null,"deprecated":null,"flags":["is_generator","is_coroutine","is_async_generator"],"fullname":"scripts.solr_dump_xisbn.stream_bounds","name":"stream_bounds","type":{".class":"CallableType","arg_kinds":[0,0,1],"arg_names":["params","solr_base","page_size"],"arg_types":[{".class":"Instance","args":["builtins.str","builtins.str"],"extra_attrs":null,"type_ref":"builtins.dict"},"builtins.str",{".class":"AnyType","missing_import_name":null,"source_any":null,"type_of_any":1}],"bound_args":[],"def_extras":{"first_arg":null},"fallback":"builtins.function","from_concatenate":false,"implicit":false,"imprecise_arg_kinds":false,"is_ellipsis_args":false,"name":"stream_bounds","ret_type":{".class":"Instance","args":[{".class":"TupleType","implicit":false,"items":["builtins.str","builtins.str"],"partial_fallback":{".class":"Instance","args":[{".class":"AnyType","missing_import_name":null,"source_any":null,"type_of_any":6}],"extra_attrs":null,"type_ref":"builtins.tuple"}},{".class":"NoneType"}],"extra_attrs":null,"type_ref":"typing.AsyncGenerator"},"type_guard":null,"type_is":null,"unpack_kwargs":false,"variables":[]}}},"sys":{".class":"SymbolTableNode","cross_ref":"sys","kind":"Gdef"}},"path":"scripts/solr_dump_xisbn.py"}