{".class":"MypyFile","_fullname":"openlibrary.core.ia","future_import_flags":[],"is_partial_stub_package":false,"is_stub":false,"names":{".class":"SymbolTable","IA_BASE_URL":{".class":"SymbolTableNode","kind":"Gdef","node":{".class":"Var","flags":["is_inferred","has_explicit_value"],"fullname":"openlibrary.core.ia.IA_BASE_URL","name":"IA_BASE_URL","type":{".class":"AnyType","missing_import_name":"openlibrary.core.ia.config","source_any":{".class":"AnyType","missing_import_name":"openlibrary.core.ia.config","source_any":null,"type_of_any":3},"type_of_any":7}}},"ItemEdition":{".class":"SymbolTableNode","kind":"Gdef","node":{".class":"TypeInfo","_promote":[],"abstract_attributes":[],"alt_promote":null,"bases":[{".class":"Instance","args":[{".class":"AnyType","missing_import_name":null,"source_any":null,"type_of_any":4},{".class":"AnyType","missing_import_name":null,"source_any":null,"type_of_any":4}],"extra_attrs":null,"type_ref":"builtins.dict"}],"dataclass_transform_spec":null,"declared_metaclass":null,"defn":{".class":"ClassDef","fullname":"openlibrary.core.ia.ItemEdition","name":"ItemEdition","type_vars":[]},"deletable_attributes":[],"deprecated":null,"flags":[],"fullname":"openlibrary.core.ia.ItemEdition","has_param_spec_type":false,"metaclass_type":"abc.ABCMeta","metadata":{},"module_name":"openlibrary.core.ia","mro":["openlibrary.core.ia.ItemEdition","builtins.dict","typing.MutableMapping","typing.Mapping","typing.Collection","typing.Iterable","typing.Container","builtins.object"],"names":{".class":"SymbolTable","__init__":{".class":"SymbolTableNode","kind":"Mdef","node":{".class":"FuncDef","abstract_status":0,"arg_kinds":[0,0],"arg_names":["self","itemid"],"dataclass_transform_spec":null,"deprecated":null,"flags":[],"fullname":"openlibrary.core.ia.ItemEdition.__init__","name":"__init__","type":null}},"add":{".class":"SymbolTableNode","kind":"Mdef","node":{".class":"FuncDef","abstract_status":0,"arg_kinds":[0,0,1],"arg_names":["self","key","key2"],"dataclass_transform_spec":null,"deprecated":null,"flags":[],"fullname":"openlibrary.core.ia.ItemEdition.add","name":"add","type":null}},"add_isbns":{".class":"SymbolTableNode","kind":"Mdef","node":{".class":"FuncDef","abstract_status":0,"arg_kinds":[0],"arg_names":["self"],"dataclass_transform_spec":null,"deprecated":null,"flags":[],"fullname":"openlibrary.core.ia.ItemEdition.add_isbns","name":"add_isbns","type":null}},"add_list":{".class":"SymbolTableNode","kind":"Mdef","node":{".class":"FuncDef","abstract_status":0,"arg_kinds":[0,0,0],"arg_names":["self","key","key2"],"dataclass_transform_spec":null,"deprecated":null,"flags":[],"fullname":"openlibrary.core.ia.ItemEdition.add_list","name":"add_list","type":null}},"add_metadata":{".class":"SymbolTableNode","kind":"Mdef","node":{".class":"FuncDef","abstract_status":0,"arg_kinds":[0,0],"arg_names":["self","metadata"],"dataclass_transform_spec":null,"deprecated":null,"flags":[],"fullname":"openlibrary.core.ia.ItemEdition.add_metadata","name":"add_metadata","type":null}},"get_item_status":{".class":"SymbolTableNode","kind":"Mdef","node":{".class":"Decorator","func":{".class":"FuncDef","abstract_status":0,"arg_kinds":[0,0,0,1,1],"arg_names":["cls","itemid","metadata","item_server","item_path"],"dataclass_transform_spec":null,"deprecated":null,"flags":["is_class","is_decorated"],"fullname":"openlibrary.core.ia.ItemEdition.get_item_status","name":"get_item_status","type":null},"is_overload":false,"var":{".class":"Var","flags":["is_initialized_in_class","is_classmethod","is_ready","is_inferred"],"fullname":"openlibrary.core.ia.ItemEdition.get_item_status","name":"get_item_status","type":{".class":"CallableType","arg_kinds":[0,0,0,1,1],"arg_names":["cls","itemid","metadata","item_server","item_path"],"arg_types":[{".class":"TypeType","item":"openlibrary.core.ia.ItemEdition"},{".class":"AnyType","missing_import_name":null,"source_any":null,"type_of_any":1},{".class":"AnyType","missing_import_name":null,"source_any":null,"type_of_any":1},{".class":"AnyType","missing_import_name":null,"source_any":null,"type_of_any":1},{".class":"AnyType","missing_import_name":null,"source_any":null,"type_of_any":1}],"bound_args":[],"def_extras":{"first_arg":"cls"},"fallback":"builtins.function","from_concatenate":false,"implicit":true,"imprecise_arg_kinds":false,"is_ellipsis_args":false,"name":"get_item_status of ItemEdition","ret_type":{".class":"AnyType","missing_import_name":null,"source_any":null,"type_of_any":1},"type_guard":null,"type_is":null,"unpack_kwargs":false,"variables":[]}}}},"is_valid_item":{".class":"SymbolTableNode","kind":"Mdef","node":{".class":"Decorator","func":{".class":"FuncDef","abstract_status":0,"arg_kinds":[0,0,0],"arg_names":["cls","itemid","metadata"],"dataclass_transform_spec":null,"deprecated":null,"flags":["is_class","is_decorated"],"fullname":"openlibrary.core.ia.ItemEdition.is_valid_item","name":"is_valid_item","type":null},"is_overload":false,"var":{".class":"Var","flags":["is_initialized_in_class","is_classmethod","is_ready","is_inferred"],"fullname":"openlibrary.core.ia.ItemEdition.is_valid_item","name":"is_valid_item","type":{".class":"CallableType","arg_kinds":[0,0,0],"arg_names":["cls","itemid","metadata"],"arg_types":[{".class":"TypeType","item":"openlibrary.core.ia.ItemEdition"},{".class":"AnyType","missing_import_name":null,"source_any":null,"type_of_any":1},{".class":"AnyType","missing_import_name":null,"source_any":null,"type_of_any":1}],"bound_args":[],"def_extras":{"first_arg":"cls"},"fallback":"builtins.function","from_concatenate":false,"implicit":true,"imprecise_arg_kinds":false,"is_ellipsis_args":false,"name":"is_valid_item of ItemEdition","ret_type":{".class":"AnyType","missing_import_name":null,"source_any":null,"type_of_any":1},"type_guard":null,"type_is":null,"unpack_kwargs":false,"variables":[]}}}},"itemid":{".class":"SymbolTableNode","implicit":true,"kind":"Mdef","node":{".class":"Var","flags":["is_inferred"],"fullname":"openlibrary.core.ia.ItemEdition.itemid","name":"itemid","type":{".class":"AnyType","missing_import_name":null,"source_any":null,"type_of_any":1}}},"metadata":{".class":"SymbolTableNode","implicit":true,"kind":"Mdef","node":{".class":"Var","flags":["is_inferred"],"fullname":"openlibrary.core.ia.ItemEdition.metadata","name":"metadata","type":{".class":"AnyType","missing_import_name":null,"source_any":null,"type_of_any":1}}}},"self_type":{".class":"TypeVarType","default":{".class":"AnyType","missing_import_name":null,"source_any":null,"type_of_any":4},"fullname":"openlibrary.core.ia.ItemEdition.Self","id":0,"name":"Self","namespace":"","upper_bound":"openlibrary.core.ia.ItemEdition","values":[],"variance":0},"slots":null,"tuple_type":null,"type_vars":[],"typeddict_type":null}},"VALID_READY_REPUB_STATES":{".class":"SymbolTableNode","kind":"Gdef","node":{".class":"Var","flags":["is_inferred","has_explicit_value"],"fullname":"openlibrary.core.ia.VALID_READY_REPUB_STATES","name":"VALID_READY_REPUB_STATES","type":{".class":"Instance","args":["builtins.str"],"extra_attrs":null,"type_ref":"builtins.list"}}},"__annotations__":{".class":"SymbolTableNode","kind":"Gdef","node":{".class":"Var","flags":["is_ready"],"fullname":"openlibrary.core.ia.__annotations__","name":"__annotations__","type":{".class":"Instance","args":["builtins.str",{".class":"AnyType","missing_import_name":null,"source_any":null,"type_of_any":6}],"extra_attrs":null,"type_ref":"builtins.dict"}}},"__doc__":{".class":"SymbolTableNode","kind":"Gdef","node":{".class":"Var","flags":["is_ready"],"fullname":"openlibrary.core.ia.__doc__","name":"__doc__","type":"builtins.str"}},"__file__":{".class":"SymbolTableNode","kind":"Gdef","node":{".class":"Var","flags":["is_ready"],"fullname":"openlibrary.core.ia.__file__","name":"__file__","type":"builtins.str"}},"__name__":{".class":"SymbolTableNode","kind":"Gdef","node":{".class":"Var","flags":["is_ready"],"fullname":"openlibrary.core.ia.__name__","name":"__name__","type":"builtins.str"}},"__package__":{".class":"SymbolTableNode","kind":"Gdef","node":{".class":"Var","flags":["is_ready"],"fullname":"openlibrary.core.ia.__package__","name":"__package__","type":"builtins.str"}},"__spec__":{".class":"SymbolTableNode","kind":"Gdef","node":{".class":"Var","flags":["is_ready"],"fullname":"openlibrary.core.ia.__spec__","name":"__spec__","type":"_frozen_importlib.ModuleSpec"}},"cache":{".class":"SymbolTableNode","cross_ref":"openlibrary.core.cache","kind":"Gdef"},"config":{".class":"SymbolTableNode","kind":"Gdef","node":{".class":"Var","flags":["is_suppressed_import","is_ready","is_inferred"],"fullname":"openlibrary.core.ia.config","name":"config","type":{".class":"AnyType","missing_import_name":"openlibrary.core.ia.config","source_any":null,"type_of_any":3}}},"datetime":{".class":"SymbolTableNode","cross_ref":"datetime","kind":"Gdef"},"edition_from_item_metadata":{".class":"SymbolTableNode","kind":"Gdef","node":{".class":"FuncDef","abstract_status":0,"arg_kinds":[0,0],"arg_names":["itemid","metadata"],"dataclass_transform_spec":null,"deprecated":null,"flags":[],"fullname":"openlibrary.core.ia.edition_from_item_metadata","name":"edition_from_item_metadata","type":null}},"extract_item_metadata":{".class":"SymbolTableNode","kind":"Gdef","node":{".class":"FuncDef","abstract_status":0,"arg_kinds":[0],"arg_names":["item_json"],"dataclass_transform_spec":null,"deprecated":null,"flags":[],"fullname":"openlibrary.core.ia.extract_item_metadata","name":"extract_item_metadata","type":null}},"get_api_response":{".class":"SymbolTableNode","kind":"Gdef","node":{".class":"FuncDef","abstract_status":0,"arg_kinds":[0,1],"arg_names":["url","params"],"dataclass_transform_spec":null,"deprecated":null,"flags":[],"fullname":"openlibrary.core.ia.get_api_response","name":"get_api_response","type":{".class":"CallableType","arg_kinds":[0,1],"arg_names":["url","params"],"arg_types":["builtins.str",{".class":"UnionType","items":[{".class":"Instance","args":[{".class":"AnyType","missing_import_name":null,"source_any":null,"type_of_any":4},{".class":"AnyType","missing_import_name":null,"source_any":null,"type_of_any":4}],"extra_attrs":null,"type_ref":"builtins.dict"},{".class":"NoneType"}],"uses_pep604_syntax":true}],"bound_args":[],"def_extras":{"first_arg":null},"fallback":"builtins.function","from_concatenate":false,"implicit":false,"imprecise_arg_kinds":false,"is_ellipsis_args":false,"name":"get_api_response","ret_type":{".class":"Instance","args":[{".class":"AnyType","missing_import_name":null,"source_any":null,"type_of_any":4},{".class":"AnyType","missing_import_name":null,"source_any":null,"type_of_any":4}],"extra_attrs":null,"type_ref":"builtins.dict"},"type_guard":null,"type_is":null,"unpack_kwargs":false,"variables":[]}}},"get_candidate_ocaids":{".class":"SymbolTableNode","kind":"Gdef","node":{".class":"FuncDef","abstract_status":0,"arg_kinds":[0,1],"arg_names":["day","marcs"],"dataclass_transform_spec":null,"deprecated":null,"flags":["is_generator"],"fullname":"openlibrary.core.ia.get_candidate_ocaids","name":"get_candidate_ocaids","type":{".class":"CallableType","arg_kinds":[0,1],"arg_names":["day","marcs"],"arg_types":["datetime.date","builtins.bool"],"bound_args":[],"def_extras":{"first_arg":null},"fallback":"builtins.function","from_concatenate":false,"implicit":false,"imprecise_arg_kinds":false,"is_ellipsis_args":false,"name":"get_candidate_ocaids","ret_type":{".class":"AnyType","missing_import_name":null,"source_any":null,"type_of_any":1},"type_guard":null,"type_is":null,"unpack_kwargs":false,"variables":[]}}},"get_candidates_url":{".class":"SymbolTableNode","kind":"Gdef","node":{".class":"FuncDef","abstract_status":0,"arg_kinds":[0,1],"arg_names":["day","marcs"],"dataclass_transform_spec":null,"deprecated":null,"flags":[],"fullname":"openlibrary.core.ia.get_candidates_url","name":"get_candidates_url","type":{".class":"CallableType","arg_kinds":[0,1],"arg_names":["day","marcs"],"arg_types":["datetime.date","builtins.bool"],"bound_args":[],"def_extras":{"first_arg":null},"fallback":"builtins.function","from_concatenate":false,"implicit":false,"imprecise_arg_kinds":false,"is_ellipsis_args":false,"name":"get_candidates_url","ret_type":"builtins.str","type_guard":null,"type_is":null,"unpack_kwargs":false,"variables":[]}}},"get_cover_url":{".class":"SymbolTableNode","kind":"Gdef","node":{".class":"FuncDef","abstract_status":0,"arg_kinds":[0],"arg_names":["item_id"],"dataclass_transform_spec":null,"deprecated":null,"flags":[],"fullname":"openlibrary.core.ia.get_cover_url","name":"get_cover_url","type":null}},"get_item_manifest":{".class":"SymbolTableNode","kind":"Gdef","node":{".class":"FuncDef","abstract_status":0,"arg_kinds":[0,0,0],"arg_names":["item_id","item_server","item_path"],"dataclass_transform_spec":null,"deprecated":null,"flags":[],"fullname":"openlibrary.core.ia.get_item_manifest","name":"get_item_manifest","type":null}},"get_item_status":{".class":"SymbolTableNode","kind":"Gdef","node":{".class":"FuncDef","abstract_status":0,"arg_kinds":[0,0,4],"arg_names":["itemid","metadata","server"],"dataclass_transform_spec":null,"deprecated":null,"flags":[],"fullname":"openlibrary.core.ia.get_item_status","name":"get_item_status","type":null}},"get_metadata":{".class":"SymbolTableNode","kind":"Gdef","node":{".class":"Var","flags":["is_inferred","has_explicit_value"],"fullname":"openlibrary.core.ia.get_metadata","name":"get_metadata","type":"openlibrary.core.cache.memcache_memoize"}},"get_metadata_direct":{".class":"SymbolTableNode","kind":"Gdef","node":{".class":"FuncDef","abstract_status":0,"arg_kinds":[0,1,1],"arg_names":["itemid","only_metadata","cache"],"dataclass_transform_spec":null,"deprecated":null,"flags":[],"fullname":"openlibrary.core.ia.get_metadata_direct","name":"get_metadata_direct","type":{".class":"CallableType","arg_kinds":[0,1,1],"arg_names":["itemid","only_metadata","cache"],"arg_types":["builtins.str","builtins.bool","builtins.bool"],"bound_args":[],"def_extras":{"first_arg":null},"fallback":"builtins.function","from_concatenate":false,"implicit":false,"imprecise_arg_kinds":false,"is_ellipsis_args":false,"name":"get_metadata_direct","ret_type":{".class":"Instance","args":[{".class":"AnyType","missing_import_name":null,"source_any":null,"type_of_any":4},{".class":"AnyType","missing_import_name":null,"source_any":null,"type_of_any":4}],"extra_attrs":null,"type_ref":"builtins.dict"},"type_guard":null,"type_is":null,"unpack_kwargs":false,"variables":[]}}},"locate_item":{".class":"SymbolTableNode","kind":"Gdef","node":{".class":"FuncDef","abstract_status":0,"arg_kinds":[0],"arg_names":["itemid"],"dataclass_transform_spec":null,"deprecated":null,"flags":[],"fullname":"openlibrary.core.ia.locate_item","name":"locate_item","type":null}},"logger":{".class":"SymbolTableNode","kind":"Gdef","node":{".class":"Var","flags":["is_inferred","has_explicit_value"],"fullname":"openlibrary.core.ia.logger","name":"logger","type":"logging.Logger"}},"logging":{".class":"SymbolTableNode","cross_ref":"logging","kind":"Gdef"},"process_metadata_dict":{".class":"SymbolTableNode","kind":"Gdef","node":{".class":"FuncDef","abstract_status":0,"arg_kinds":[0],"arg_names":["metadata"],"dataclass_transform_spec":null,"deprecated":null,"flags":[],"fullname":"openlibrary.core.ia.process_metadata_dict","name":"process_metadata_dict","type":null}},"requests":{".class":"SymbolTableNode","cross_ref":"requests","kind":"Gdef"},"stats":{".class":"SymbolTableNode","kind":"Gdef","node":{".class":"Var","flags":["is_suppressed_import","is_ready","is_inferred"],"fullname":"openlibrary.core.ia.stats","name":"stats","type":{".class":"AnyType","missing_import_name":"openlibrary.core.ia.stats","source_any":null,"type_of_any":3}}},"urlencode":{".class":"SymbolTableNode","cross_ref":"urllib.parse.urlencode","kind":"Gdef"},"web":{".class":"SymbolTableNode","kind":"Gdef","node":{".class":"Var","flags":["is_suppressed_import","is_ready","is_inferred"],"fullname":"openlibrary.core.ia.web","name":"web","type":{".class":"AnyType","missing_import_name":"openlibrary.core.ia.web","source_any":null,"type_of_any":3}}}},"path":"openlibrary\\core\\ia.py"}